fsm_effective_stress.py
fsm_effective_stress-1.0.1.dist-info/DESCRIPTION.rst
fsm_effective_stress-1.0.1.dist-info/METADATA
fsm_effective_stress-1.0.1.dist-info/RECORD
fsm_effective_stress-1.0.1.dist-info/WHEEL
fsm_effective_stress-1.0.1.dist-info/metadata.json
fsm_effective_stress-1.0.1.dist-info/top_level.txt
